{
    "semester": {
        "id": "bca5",
        "subjects": {
            "theory": [
                {
                    "subjectName": "COMPUTER GRAPHICS",
                    "code": "CA301",
                    "credit": 3,
                    "sortName": "CG"
                },
                {
                    "subjectName": "INTRODUCTION TO COMPUTER NETWORKS",
                    "code": "CA303",
                    "credit": 3,
                    "sortName": "ITCN"
                }
            ],
            "lab": [
                {
                    "subjectName": "COMPUTER GRAPHICS LAB",
                    "code": "CA302",
                    "shortName": "java lab",
                    "credit": 2
                },
                {
                    "subjectName": "COMPUTER NETWORKS LAB",
                    "code": "CA308",
                    "shortName": "dbms lab",
                    "credit": 2
                }
            ],
            "pe": [
                {
                    "subjectName": "INTRODUCTION TO PYTHON PROGRAMMING",
                    "code": "CA309",
                    "credit": 4,
                    "sortName": "ITPP"
                },
                {
                    "subjectName": "INTRODUCTION TO PYTHON PROGRAMMING LAB",
                    "code": "CA310",
                    "credit": 2,
                    "sortName": "ITPPL"
                },
                {
                    "subjectName": "INTRODUCTION TO INTERNET TECHNOLOGIES",
                    "code": "CA317",
                    "credit": 4,
                    "sortName": "IT"
                },
                {
                    "subjectName": "INTERNET TECHNOLOGIES LAB",
                    "code": "CA318",
                    "credit": 2,
                    "sortName": "ITL"
                }
            ]
        }
    }
}